{"Model::Mesh::ElementGeometry": [{"dtype": "compas.datastructures/Mesh", "data": {"attributes": {"is_support": true}, "default_vertex_attributes": {"x": 0.0, "y": 0.0, "z": 0.0}, "default_edge_attributes": {}, "default_face_attributes": {}, "vertex": {"0": {"x": 2951.923076923077, "y": -3000.0, "z": 3.410605131648481e-13}, "1": {"x": 3048.0769230769233, "y": -3000.0, "z": 230.76923076923106}, "2": {"x": 1801.059405019541, "y": -3000.0, "z": 376.06890166765487}, "3": {"x": 1859.7258351504702, "y": -3000.0, "z": 619.0879337941382}, "4": {"x": 2951.923076923077, "y": -1800.0, "z": 3.410605131648481e-13}, "5": {"x": 3048.0769230769233, "y": -1800.0, "z": 230.76923076923106}, "6": {"x": 1801.059405019541, "y": -1800.0, "z": 376.06890166765487}, "7": {"x": 1859.7258351504702, "y": -1800.0, "z": 619.0879337941382}}, "face": {"0": [0, 1, 3, 2], "1": [0, 4, 5, 1], "2": [4, 6, 7, 5], "3": [6, 2, 3, 7], "4": [1, 5, 7, 3], "5": [2, 6, 4, 0]}, "facedata": {"0": {}, "1": {}, "2": {}, "3": {}, "4": {}, "5": {}}, "edgedata": {}, "max_vertex": 7, "max_face": 5}, "guid": "4a13b3a5-ea24-4ff9-94d8-4d9cd4867a11"}, {"dtype": "compas.datastructures/Mesh", "data": {"attributes": {"is_support": false}, "default_vertex_attributes": {"x": 0.0, "y": 0.0, "z": 0.0}, "default_edge_attributes": {}, "default_face_attributes": {}, "vertex": {"0": {"x": 1801.059405019541, "y": -2400.0, "z": 376.06890166765487}, "1": {"x": 1859.7258351504702, "y": -2400.0, "z": 619.0879337941382}, "2": {"x": 605.3748859402758, "y": -2400.0, "z": 566.4725280590476}, "3": {"x": 625.0939375995681, "y": -2400.0, "z": 815.6936327064232}, "4": {"x": 1801.059405019541, "y": -1200.0, "z": 376.06890166765487}, "5": {"x": 1859.7258351504702, "y": -1200.0, "z": 619.0879337941382}, "6": {"x": 605.3748859402758, "y": -1200.0, "z": 566.4725280590476}, "7": {"x": 625.0939375995681, "y": -1200.0, "z": 815.6936327064232}}, "face": {"0": [0, 1, 3, 2], "1": [0, 4, 5, 1], "2": [4, 6, 7, 5], "3": [6, 2, 3, 7], "4": [1, 5, 7, 3], "5": [2, 6, 4, 0]}, "facedata": {"0": {}, "1": {}, "2": {}, "3": {}, "4": {}, "5": {}}, "edgedata": {}, "max_vertex": 7, "max_face": 5}, "guid": "20053c50-6b3e-4c40-886d-502cdfcff3cf"}, {"dtype": "compas.datastructures/Mesh", "data": {"attributes": {"is_support": false}, "default_vertex_attributes": {"x": 0.0, "y": 0.0, "z": 0.0}, "default_edge_attributes": {}, "default_face_attributes": {}, "vertex": {"0": {"x": 605.3748859402758, "y": -3000.0, "z": 566.4725280590476}, "1": {"x": 625.0939375995681, "y": -3000.0, "z": 815.6936327064232}, "2": {"x": -605.3748859402749, "y": -3000.0, "z": 566.4725280590478}, "3": {"x": -625.0939375995672, "y": -3000.0, "z": 815.6936327064236}, "4": {"x": 605.3748859402758, "y": -1800.0, "z": 566.4725280590476}, "5": {"x": 625.0939375995681, "y": -1800.0, "z": 815.6936327064232}, "6": {"x": -605.3748859402749, "y": -1800.0, "z": 566.4725280590478}, "7": {"x": -625.0939375995672, "y": -1800.0, "z": 815.6936327064236}}, "face": {"0": [0, 1, 3, 2], "1": [0, 4, 5, 1], "2": [4, 6, 7, 5], "3": [6, 2, 3, 7], "4": [1, 5, 7, 3], "5": [2, 6, 4, 0]}, "facedata": {"0": {}, "1": {}, "2": {}, "3": {}, "4": {}, "5": {}}, "edgedata": {}, "max_vertex": 7, "max_face": 5}, "guid": "d2b87b4e-895f-4e0d-86d2-6a32fc3b4e2c"}, {"dtype": "compas.datastructures/Mesh", "data": {"attributes": {"is_support": false}, "default_vertex_attributes": {"x": 0.0, "y": 0.0, "z": 0.0}, "default_edge_attributes": {}, "default_face_attributes": {}, "vertex": {"0": {"x": -605.3748859402749, "y": -2400.0, "z": 566.4725280590478}, "1": {"x": -625.0939375995672, "y": -2400.0, "z": 815.6936327064236}, "2": {"x": -1801.05940501954, "y": -2400.0, "z": 376.0689016676545}, "3": {"x": -1859.7258351504697, "y": -2400.0, "z": 619.0879337941378}, "4": {"x": -605.3748859402749, "y": -1200.0, "z": 566.4725280590478}, "5": {"x": -625.0939375995672, "y": -1200.0, "z": 815.6936327064236}, "6": {"x": -1801.05940501954, "y": -1200.0, "z": 376.0689016676545}, "7": {"x": -1859.7258351504697, "y": -1200.0, "z": 619.0879337941378}}, "face": {"0": [0, 1, 3, 2], "1": [0, 4, 5, 1], "2": [4, 6, 7, 5], "3": [6, 2, 3, 7], "4": [1, 5, 7, 3], "5": [2, 6, 4, 0]}, "facedata": {"0": {}, "1": {}, "2": {}, "3": {}, "4": {}, "5": {}}, "edgedata": {}, "max_vertex": 7, "max_face": 5}, "guid": "59d69a1e-d36e-4554-9922-4b1ca87e2aaa"}, {"dtype": "compas.datastructures/Mesh", "data": {"attributes": {"is_support": true}, "default_vertex_attributes": {"x": 0.0, "y": 0.0, "z": 0.0}, "default_edge_attributes": {}, "default_face_attributes": {}, "vertex": {"0": {"x": -1801.05940501954, "y": -3000.0, "z": 376.0689016676545}, "1": {"x": -1859.7258351504697, "y": -3000.0, "z": 619.0879337941378}, "2": {"x": -2951.9230769230776, "y": -3000.0, "z": 0.0}, "3": {"x": -3048.0769230769233, "y": -3000.0, "z": 230.7692307692305}, "4": {"x": -1801.05940501954, "y": -1800.0, "z": 376.0689016676545}, "5": {"x": -1859.7258351504697, "y": -1800.0, "z": 619.0879337941378}, "6": {"x": -2951.9230769230776, "y": -1800.0, "z": 0.0}, "7": {"x": -3048.0769230769233, "y": -1800.0, "z": 230.7692307692305}}, "face": {"0": [0, 1, 3, 2], "1": [0, 4, 5, 1], "2": [4, 6, 7, 5], "3": [6, 2, 3, 7], "4": [1, 5, 7, 3], "5": [2, 6, 4, 0]}, "facedata": {"0": {}, "1": {}, "2": {}, "3": {}, "4": {}, "5": {}}, "edgedata": {}, "max_vertex": 7, "max_face": 5}, "guid": "e41cd1cf-1406-478f-aeae-cbf78bf9e3e1"}, {"dtype": "compas.datastructures/Mesh", "data": {"attributes": {"is_support": true}, "default_vertex_attributes": {"x": 0.0, "y": 0.0, "z": 0.0}, "default_edge_attributes": {}, "default_face_attributes": {}, "vertex": {"0": {"x": 2951.923076923077, "y": -1800.0, "z": 3.410605131648481e-13}, "1": {"x": 3048.0769230769233, "y": -1800.0, "z": 230.76923076923106}, "2": {"x": 1801.059405019541, "y": -1800.0, "z": 376.06890166765487}, "3": {"x": 1859.7258351504702, "y": -1800.0, "z": 619.0879337941382}, "4": {"x": 2951.923076923077, "y": -600.0, "z": 3.410605131648481e-13}, "5": {"x": 3048.0769230769233, "y": -600.0, "z": 230.76923076923106}, "6": {"x": 1801.059405019541, "y": -600.0, "z": 376.06890166765487}, "7": {"x": 1859.7258351504702, "y": -600.0, "z": 619.0879337941382}}, "face": {"0": [0, 1, 3, 2], "1": [0, 4, 5, 1], "2": [4, 6, 7, 5], "3": [6, 2, 3, 7], "4": [1, 5, 7, 3], "5": [2, 6, 4, 0]}, "facedata": {"0": {}, "1": {}, "2": {}, "3": {}, "4": {}, "5": {}}, "edgedata": {}, "max_vertex": 7, "max_face": 5}, "guid": "503dd000-d3ee-4cb7-8f3a-e2e6a537df60"}, {"dtype": "compas.datastructures/Mesh", "data": {"attributes": {"is_support": false}, "default_vertex_attributes": {"x": 0.0, "y": 0.0, "z": 0.0}, "default_edge_attributes": {}, "default_face_attributes": {}, "vertex": {"0": {"x": 1801.059405019541, "y": -1200.0, "z": 376.06890166765487}, "1": {"x": 1859.7258351504702, "y": -1200.0, "z": 619.0879337941382}, "2": {"x": 605.3748859402758, "y": -1200.0, "z": 566.4725280590476}, "3": {"x": 625.0939375995681, "y": -1200.0, "z": 815.6936327064232}, "4": {"x": 1801.059405019541, "y": 0.0, "z": 376.06890166765487}, "5": {"x": 1859.7258351504702, "y": 0.0, "z": 619.0879337941382}, "6": {"x": 605.3748859402758, "y": 0.0, "z": 566.4725280590476}, "7": {"x": 625.0939375995681, "y": 0.0, "z": 815.6936327064232}}, "face": {"0": [0, 1, 3, 2], "1": [0, 4, 5, 1], "2": [4, 6, 7, 5], "3": [6, 2, 3, 7], "4": [1, 5, 7, 3], "5": [2, 6, 4, 0]}, "facedata": {"0": {}, "1": {}, "2": {}, "3": {}, "4": {}, "5": {}}, "edgedata": {}, "max_vertex": 7, "max_face": 5}, "guid": "8c394810-1234-4898-9f36-d06ce945fe8c"}, {"dtype": "compas.datastructures/Mesh", "data": {"attributes": {"is_support": false}, "default_vertex_attributes": {"x": 0.0, "y": 0.0, "z": 0.0}, "default_edge_attributes": {}, "default_face_attributes": {}, "vertex": {"0": {"x": 605.3748859402758, "y": -1800.0, "z": 566.4725280590476}, "1": {"x": 625.0939375995681, "y": -1800.0, "z": 815.6936327064232}, "2": {"x": -605.3748859402749, "y": -1800.0, "z": 566.4725280590478}, "3": {"x": -625.0939375995672, "y": -1800.0, "z": 815.6936327064236}, "4": {"x": 605.3748859402758, "y": -600.0, "z": 566.4725280590476}, "5": {"x": 625.0939375995681, "y": -600.0, "z": 815.6936327064232}, "6": {"x": -605.3748859402749, "y": -600.0, "z": 566.4725280590478}, "7": {"x": -625.0939375995672, "y": -600.0, "z": 815.6936327064236}}, "face": {"0": [0, 1, 3, 2], "1": [0, 4, 5, 1], "2": [4, 6, 7, 5], "3": [6, 2, 3, 7], "4": [1, 5, 7, 3], "5": [2, 6, 4, 0]}, "facedata": {"0": {}, "1": {}, "2": {}, "3": {}, "4": {}, "5": {}}, "edgedata": {}, "max_vertex": 7, "max_face": 5}, "guid": "6ec9960f-6097-4b37-b469-5dbab6ade09a"}, {"dtype": "compas.datastructures/Mesh", "data": {"attributes": {"is_support": false}, "default_vertex_attributes": {"x": 0.0, "y": 0.0, "z": 0.0}, "default_edge_attributes": {}, "default_face_attributes": {}, "vertex": {"0": {"x": -605.3748859402749, "y": -1200.0, "z": 566.4725280590478}, "1": {"x": -625.0939375995672, "y": -1200.0, "z": 815.6936327064236}, "2": {"x": -1801.05940501954, "y": -1200.0, "z": 376.0689016676545}, "3": {"x": -1859.7258351504697, "y": -1200.0, "z": 619.0879337941378}, "4": {"x": -605.3748859402749, "y": 0.0, "z": 566.4725280590478}, "5": {"x": -625.0939375995672, "y": 0.0, "z": 815.6936327064236}, "6": {"x": -1801.05940501954, "y": 0.0, "z": 376.0689016676545}, "7": {"x": -1859.7258351504697, "y": 0.0, "z": 619.0879337941378}}, "face": {"0": [0, 1, 3, 2], "1": [0, 4, 5, 1], "2": [4, 6, 7, 5], "3": [6, 2, 3, 7], "4": [1, 5, 7, 3], "5": [2, 6, 4, 0]}, "facedata": {"0": {}, "1": {}, "2": {}, "3": {}, "4": {}, "5": {}}, "edgedata": {}, "max_vertex": 7, "max_face": 5}, "guid": "0816bae7-4c7d-4711-9cd7-01805cd73463"}, {"dtype": "compas.datastructures/Mesh", "data": {"attributes": {"is_support": true}, "default_vertex_attributes": {"x": 0.0, "y": 0.0, "z": 0.0}, "default_edge_attributes": {}, "default_face_attributes": {}, "vertex": {"0": {"x": -1801.05940501954, "y": -1800.0, "z": 376.0689016676545}, "1": {"x": -1859.7258351504697, "y": -1800.0, "z": 619.0879337941378}, "2": {"x": -2951.9230769230776, "y": -1800.0, "z": 0.0}, "3": {"x": -3048.0769230769233, "y": -1800.0, "z": 230.7692307692305}, "4": {"x": -1801.05940501954, "y": -600.0, "z": 376.0689016676545}, "5": {"x": -1859.7258351504697, "y": -600.0, "z": 619.0879337941378}, "6": {"x": -2951.9230769230776, "y": -600.0, "z": 0.0}, "7": {"x": -3048.0769230769233, "y": -600.0, "z": 230.7692307692305}}, "face": {"0": [0, 1, 3, 2], "1": [0, 4, 5, 1], "2": [4, 6, 7, 5], "3": [6, 2, 3, 7], "4": [1, 5, 7, 3], "5": [2, 6, 4, 0]}, "facedata": {"0": {}, "1": {}, "2": {}, "3": {}, "4": {}, "5": {}}, "edgedata": {}, "max_vertex": 7, "max_face": 5}, "guid": "c306b4b5-ca3c-4c34-9bdf-67de079bf6e6"}, {"dtype": "compas.datastructures/Mesh", "data": {"attributes": {"is_support": true}, "default_vertex_attributes": {"x": 0.0, "y": 0.0, "z": 0.0}, "default_edge_attributes": {}, "default_face_attributes": {}, "vertex": {"0": {"x": 2951.923076923077, "y": -600.0, "z": 3.410605131648481e-13}, "1": {"x": 3048.0769230769233, "y": -600.0, "z": 230.76923076923106}, "2": {"x": 1801.059405019541, "y": -600.0, "z": 376.06890166765487}, "3": {"x": 1859.7258351504702, "y": -600.0, "z": 619.0879337941382}, "4": {"x": 2951.923076923077, "y": 600.0, "z": 3.410605131648481e-13}, "5": {"x": 3048.0769230769233, "y": 600.0, "z": 230.76923076923106}, "6": {"x": 1801.059405019541, "y": 600.0, "z": 376.06890166765487}, "7": {"x": 1859.7258351504702, "y": 600.0, "z": 619.0879337941382}}, "face": {"0": [0, 1, 3, 2], "1": [0, 4, 5, 1], "2": [4, 6, 7, 5], "3": [6, 2, 3, 7], "4": [1, 5, 7, 3], "5": [2, 6, 4, 0]}, "facedata": {"0": {}, "1": {}, "2": {}, "3": {}, "4": {}, "5": {}}, "edgedata": {}, "max_vertex": 7, "max_face": 5}, "guid": "62a7c10d-0446-419e-8176-90072e256e8c"}, {"dtype": "compas.datastructures/Mesh", "data": {"attributes": {"is_support": false}, "default_vertex_attributes": {"x": 0.0, "y": 0.0, "z": 0.0}, "default_edge_attributes": {}, "default_face_attributes": {}, "vertex": {"0": {"x": 1801.059405019541, "y": 0.0, "z": 376.06890166765487}, "1": {"x": 1859.7258351504702, "y": 0.0, "z": 619.0879337941382}, "2": {"x": 605.3748859402758, "y": 0.0, "z": 566.4725280590476}, "3": {"x": 625.0939375995681, "y": 0.0, "z": 815.6936327064232}, "4": {"x": 1801.059405019541, "y": 1200.0, "z": 376.06890166765487}, "5": {"x": 1859.7258351504702, "y": 1200.0, "z": 619.0879337941382}, "6": {"x": 605.3748859402758, "y": 1200.0, "z": 566.4725280590476}, "7": {"x": 625.0939375995681, "y": 1200.0, "z": 815.6936327064232}}, "face": {"0": [0, 1, 3, 2], "1": [0, 4, 5, 1], "2": [4, 6, 7, 5], "3": [6, 2, 3, 7], "4": [1, 5, 7, 3], "5": [2, 6, 4, 0]}, "facedata": {"0": {}, "1": {}, "2": {}, "3": {}, "4": {}, "5": {}}, "edgedata": {}, "max_vertex": 7, "max_face": 5}, "guid": "b49d0f79-9735-4075-9a77-af738eb15c57"}, {"dtype": "compas.datastructures/Mesh", "data": {"attributes": {"is_support": false}, "default_vertex_attributes": {"x": 0.0, "y": 0.0, "z": 0.0}, "default_edge_attributes": {}, "default_face_attributes": {}, "vertex": {"0": {"x": 605.3748859402758, "y": -600.0, "z": 566.4725280590476}, "1": {"x": 625.0939375995681, "y": -600.0, "z": 815.6936327064232}, "2": {"x": -605.3748859402749, "y": -600.0, "z": 566.4725280590478}, "3": {"x": -625.0939375995672, "y": -600.0, "z": 815.6936327064236}, "4": {"x": 605.3748859402758, "y": 600.0, "z": 566.4725280590476}, "5": {"x": 625.0939375995681, "y": 600.0, "z": 815.6936327064232}, "6": {"x": -605.3748859402749, "y": 600.0, "z": 566.4725280590478}, "7": {"x": -625.0939375995672, "y": 600.0, "z": 815.6936327064236}}, "face": {"0": [0, 1, 3, 2], "1": [0, 4, 5, 1], "2": [4, 6, 7, 5], "3": [6, 2, 3, 7], "4": [1, 5, 7, 3], "5": [2, 6, 4, 0]}, "facedata": {"0": {}, "1": {}, "2": {}, "3": {}, "4": {}, "5": {}}, "edgedata": {}, "max_vertex": 7, "max_face": 5}, "guid": "32649224-1ba1-4843-99d3-914203cf523a"}, {"dtype": "compas.datastructures/Mesh", "data": {"attributes": {"is_support": false}, "default_vertex_attributes": {"x": 0.0, "y": 0.0, "z": 0.0}, "default_edge_attributes": {}, "default_face_attributes": {}, "vertex": {"0": {"x": -605.3748859402749, "y": 0.0, "z": 566.4725280590478}, "1": {"x": -625.0939375995672, "y": 0.0, "z": 815.6936327064236}, "2": {"x": -1801.05940501954, "y": 0.0, "z": 376.0689016676545}, "3": {"x": -1859.7258351504697, "y": 0.0, "z": 619.0879337941378}, "4": {"x": -605.3748859402749, "y": 1200.0, "z": 566.4725280590478}, "5": {"x": -625.0939375995672, "y": 1200.0, "z": 815.6936327064236}, "6": {"x": -1801.05940501954, "y": 1200.0, "z": 376.0689016676545}, "7": {"x": -1859.7258351504697, "y": 1200.0, "z": 619.0879337941378}}, "face": {"0": [0, 1, 3, 2], "1": [0, 4, 5, 1], "2": [4, 6, 7, 5], "3": [6, 2, 3, 7], "4": [1, 5, 7, 3], "5": [2, 6, 4, 0]}, "facedata": {"0": {}, "1": {}, "2": {}, "3": {}, "4": {}, "5": {}}, "edgedata": {}, "max_vertex": 7, "max_face": 5}, "guid": "e00e2308-5e6b-40ca-9e84-9c3eba31f4e0"}, {"dtype": "compas.datastructures/Mesh", "data": {"attributes": {"is_support": true}, "default_vertex_attributes": {"x": 0.0, "y": 0.0, "z": 0.0}, "default_edge_attributes": {}, "default_face_attributes": {}, "vertex": {"0": {"x": -1801.05940501954, "y": -600.0, "z": 376.0689016676545}, "1": {"x": -1859.7258351504697, "y": -600.0, "z": 619.0879337941378}, "2": {"x": -2951.9230769230776, "y": -600.0, "z": 0.0}, "3": {"x": -3048.0769230769233, "y": -600.0, "z": 230.7692307692305}, "4": {"x": -1801.05940501954, "y": 600.0, "z": 376.0689016676545}, "5": {"x": -1859.7258351504697, "y": 600.0, "z": 619.0879337941378}, "6": {"x": -2951.9230769230776, "y": 600.0, "z": 0.0}, "7": {"x": -3048.0769230769233, "y": 600.0, "z": 230.7692307692305}}, "face": {"0": [0, 1, 3, 2], "1": [0, 4, 5, 1], "2": [4, 6, 7, 5], "3": [6, 2, 3, 7], "4": [1, 5, 7, 3], "5": [2, 6, 4, 0]}, "facedata": {"0": {}, "1": {}, "2": {}, "3": {}, "4": {}, "5": {}}, "edgedata": {}, "max_vertex": 7, "max_face": 5}, "guid": "7219f9fc-a467-4c3e-956a-6e61988c81a0"}, {"dtype": "compas.datastructures/Mesh", "data": {"attributes": {"is_support": true}, "default_vertex_attributes": {"x": 0.0, "y": 0.0, "z": 0.0}, "default_edge_attributes": {}, "default_face_attributes": {}, "vertex": {"0": {"x": 2951.923076923077, "y": 600.0, "z": 3.410605131648481e-13}, "1": {"x": 3048.0769230769233, "y": 600.0, "z": 230.76923076923106}, "2": {"x": 1801.059405019541, "y": 600.0, "z": 376.06890166765487}, "3": {"x": 1859.7258351504702, "y": 600.0, "z": 619.0879337941382}, "4": {"x": 2951.923076923077, "y": 1800.0, "z": 3.410605131648481e-13}, "5": {"x": 3048.0769230769233, "y": 1800.0, "z": 230.76923076923106}, "6": {"x": 1801.059405019541, "y": 1800.0, "z": 376.06890166765487}, "7": {"x": 1859.7258351504702, "y": 1800.0, "z": 619.0879337941382}}, "face": {"0": [0, 1, 3, 2], "1": [0, 4, 5, 1], "2": [4, 6, 7, 5], "3": [6, 2, 3, 7], "4": [1, 5, 7, 3], "5": [2, 6, 4, 0]}, "facedata": {"0": {}, "1": {}, "2": {}, "3": {}, "4": {}, "5": {}}, "edgedata": {}, "max_vertex": 7, "max_face": 5}, "guid": "84597719-484d-4fc7-94dc-b30599c9cdbd"}, {"dtype": "compas.datastructures/Mesh", "data": {"attributes": {"is_support": false}, "default_vertex_attributes": {"x": 0.0, "y": 0.0, "z": 0.0}, "default_edge_attributes": {}, "default_face_attributes": {}, "vertex": {"0": {"x": 1801.059405019541, "y": 1200.0, "z": 376.06890166765487}, "1": {"x": 1859.7258351504702, "y": 1200.0, "z": 619.0879337941382}, "2": {"x": 605.3748859402758, "y": 1200.0, "z": 566.4725280590476}, "3": {"x": 625.0939375995681, "y": 1200.0, "z": 815.6936327064232}, "4": {"x": 1801.059405019541, "y": 2400.0, "z": 376.06890166765487}, "5": {"x": 1859.7258351504702, "y": 2400.0, "z": 619.0879337941382}, "6": {"x": 605.3748859402758, "y": 2400.0, "z": 566.4725280590476}, "7": {"x": 625.0939375995681, "y": 2400.0, "z": 815.6936327064232}}, "face": {"0": [0, 1, 3, 2], "1": [0, 4, 5, 1], "2": [4, 6, 7, 5], "3": [6, 2, 3, 7], "4": [1, 5, 7, 3], "5": [2, 6, 4, 0]}, "facedata": {"0": {}, "1": {}, "2": {}, "3": {}, "4": {}, "5": {}}, "edgedata": {}, "max_vertex": 7, "max_face": 5}, "guid": "6e2b4076-da6e-487c-a098-65a44f9118a6"}, {"dtype": "compas.datastructures/Mesh", "data": {"attributes": {"is_support": false}, "default_vertex_attributes": {"x": 0.0, "y": 0.0, "z": 0.0}, "default_edge_attributes": {}, "default_face_attributes": {}, "vertex": {"0": {"x": 605.3748859402758, "y": 600.0, "z": 566.4725280590476}, "1": {"x": 625.0939375995681, "y": 600.0, "z": 815.6936327064232}, "2": {"x": -605.3748859402749, "y": 600.0, "z": 566.4725280590478}, "3": {"x": -625.0939375995672, "y": 600.0, "z": 815.6936327064236}, "4": {"x": 605.3748859402758, "y": 1800.0, "z": 566.4725280590476}, "5": {"x": 625.0939375995681, "y": 1800.0, "z": 815.6936327064232}, "6": {"x": -605.3748859402749, "y": 1800.0, "z": 566.4725280590478}, "7": {"x": -625.0939375995672, "y": 1800.0, "z": 815.6936327064236}}, "face": {"0": [0, 1, 3, 2], "1": [0, 4, 5, 1], "2": [4, 6, 7, 5], "3": [6, 2, 3, 7], "4": [1, 5, 7, 3], "5": [2, 6, 4, 0]}, "facedata": {"0": {}, "1": {}, "2": {}, "3": {}, "4": {}, "5": {}}, "edgedata": {}, "max_vertex": 7, "max_face": 5}, "guid": "2a8cd46c-cab4-400c-bc19-b90588236852"}, {"dtype": "compas.datastructures/Mesh", "data": {"attributes": {"is_support": false}, "default_vertex_attributes": {"x": 0.0, "y": 0.0, "z": 0.0}, "default_edge_attributes": {}, "default_face_attributes": {}, "vertex": {"0": {"x": -605.3748859402749, "y": 1200.0, "z": 566.4725280590478}, "1": {"x": -625.0939375995672, "y": 1200.0, "z": 815.6936327064236}, "2": {"x": -1801.05940501954, "y": 1200.0, "z": 376.0689016676545}, "3": {"x": -1859.7258351504697, "y": 1200.0, "z": 619.0879337941378}, "4": {"x": -605.3748859402749, "y": 2400.0, "z": 566.4725280590478}, "5": {"x": -625.0939375995672, "y": 2400.0, "z": 815.6936327064236}, "6": {"x": -1801.05940501954, "y": 2400.0, "z": 376.0689016676545}, "7": {"x": -1859.7258351504697, "y": 2400.0, "z": 619.0879337941378}}, "face": {"0": [0, 1, 3, 2], "1": [0, 4, 5, 1], "2": [4, 6, 7, 5], "3": [6, 2, 3, 7], "4": [1, 5, 7, 3], "5": [2, 6, 4, 0]}, "facedata": {"0": {}, "1": {}, "2": {}, "3": {}, "4": {}, "5": {}}, "edgedata": {}, "max_vertex": 7, "max_face": 5}, "guid": "9be4cb3e-2281-438e-892d-0eea0da2eb4d"}, {"dtype": "compas.datastructures/Mesh", "data": {"attributes": {"is_support": true}, "default_vertex_attributes": {"x": 0.0, "y": 0.0, "z": 0.0}, "default_edge_attributes": {}, "default_face_attributes": {}, "vertex": {"0": {"x": -1801.05940501954, "y": 600.0, "z": 376.0689016676545}, "1": {"x": -1859.7258351504697, "y": 600.0, "z": 619.0879337941378}, "2": {"x": -2951.9230769230776, "y": 600.0, "z": 0.0}, "3": {"x": -3048.0769230769233, "y": 600.0, "z": 230.7692307692305}, "4": {"x": -1801.05940501954, "y": 1800.0, "z": 376.0689016676545}, "5": {"x": -1859.7258351504697, "y": 1800.0, "z": 619.0879337941378}, "6": {"x": -2951.9230769230776, "y": 1800.0, "z": 0.0}, "7": {"x": -3048.0769230769233, "y": 1800.0, "z": 230.7692307692305}}, "face": {"0": [0, 1, 3, 2], "1": [0, 4, 5, 1], "2": [4, 6, 7, 5], "3": [6, 2, 3, 7], "4": [1, 5, 7, 3], "5": [2, 6, 4, 0]}, "facedata": {"0": {}, "1": {}, "2": {}, "3": {}, "4": {}, "5": {}}, "edgedata": {}, "max_vertex": 7, "max_face": 5}, "guid": "be5876a0-415d-4fb1-88cb-b29401d03972"}, {"dtype": "compas.datastructures/Mesh", "data": {"attributes": {"is_support": true}, "default_vertex_attributes": {"x": 0.0, "y": 0.0, "z": 0.0}, "default_edge_attributes": {}, "default_face_attributes": {}, "vertex": {"0": {"x": 2951.923076923077, "y": 1800.0, "z": 3.410605131648481e-13}, "1": {"x": 3048.0769230769233, "y": 1800.0, "z": 230.76923076923106}, "2": {"x": 1801.059405019541, "y": 1800.0, "z": 376.06890166765487}, "3": {"x": 1859.7258351504702, "y": 1800.0, "z": 619.0879337941382}, "4": {"x": 2951.923076923077, "y": 3000.0, "z": 3.410605131648481e-13}, "5": {"x": 3048.0769230769233, "y": 3000.0, "z": 230.76923076923106}, "6": {"x": 1801.059405019541, "y": 3000.0, "z": 376.06890166765487}, "7": {"x": 1859.7258351504702, "y": 3000.0, "z": 619.0879337941382}}, "face": {"0": [0, 1, 3, 2], "1": [0, 4, 5, 1], "2": [4, 6, 7, 5], "3": [6, 2, 3, 7], "4": [1, 5, 7, 3], "5": [2, 6, 4, 0]}, "facedata": {"0": {}, "1": {}, "2": {}, "3": {}, "4": {}, "5": {}}, "edgedata": {}, "max_vertex": 7, "max_face": 5}, "guid": "5ed36a35-6bd8-4d88-bb14-a7e39b797cea"}, {"dtype": "compas.datastructures/Mesh", "data": {"attributes": {"is_support": false}, "default_vertex_attributes": {"x": 0.0, "y": 0.0, "z": 0.0}, "default_edge_attributes": {}, "default_face_attributes": {}, "vertex": {"0": {"x": 605.3748859402758, "y": 1800.0, "z": 566.4725280590476}, "1": {"x": 625.0939375995681, "y": 1800.0, "z": 815.6936327064232}, "2": {"x": -605.3748859402749, "y": 1800.0, "z": 566.4725280590478}, "3": {"x": -625.0939375995672, "y": 1800.0, "z": 815.6936327064236}, "4": {"x": 605.3748859402758, "y": 3000.0, "z": 566.4725280590476}, "5": {"x": 625.0939375995681, "y": 3000.0, "z": 815.6936327064232}, "6": {"x": -605.3748859402749, "y": 3000.0, "z": 566.4725280590478}, "7": {"x": -625.0939375995672, "y": 3000.0, "z": 815.6936327064236}}, "face": {"0": [0, 1, 3, 2], "1": [0, 4, 5, 1], "2": [4, 6, 7, 5], "3": [6, 2, 3, 7], "4": [1, 5, 7, 3], "5": [2, 6, 4, 0]}, "facedata": {"0": {}, "1": {}, "2": {}, "3": {}, "4": {}, "5": {}}, "edgedata": {}, "max_vertex": 7, "max_face": 5}, "guid": "aa9402b8-53e7-4d35-b269-ee2396d76e56"}, {"dtype": "compas.datastructures/Mesh", "data": {"attributes": {"is_support": true}, "default_vertex_attributes": {"x": 0.0, "y": 0.0, "z": 0.0}, "default_edge_attributes": {}, "default_face_attributes": {}, "vertex": {"0": {"x": -1801.05940501954, "y": 1800.0, "z": 376.0689016676545}, "1": {"x": -1859.7258351504697, "y": 1800.0, "z": 619.0879337941378}, "2": {"x": -2951.9230769230776, "y": 1800.0, "z": 0.0}, "3": {"x": -3048.0769230769233, "y": 1800.0, "z": 230.7692307692305}, "4": {"x": -1801.05940501954, "y": 3000.0, "z": 376.0689016676545}, "5": {"x": -1859.7258351504697, "y": 3000.0, "z": 619.0879337941378}, "6": {"x": -2951.9230769230776, "y": 3000.0, "z": 0.0}, "7": {"x": -3048.0769230769233, "y": 3000.0, "z": 230.7692307692305}}, "face": {"0": [0, 1, 3, 2], "1": [0, 4, 5, 1], "2": [4, 6, 7, 5], "3": [6, 2, 3, 7], "4": [1, 5, 7, 3], "5": [2, 6, 4, 0]}, "facedata": {"0": {}, "1": {}, "2": {}, "3": {}, "4": {}, "5": {}}, "edgedata": {}, "max_vertex": 7, "max_face": 5}, "guid": "a60dabd5-d63c-448b-9eb1-ef766d10598a"}, {"dtype": "compas.datastructures/Mesh", "data": {"attributes": {"is_support": false}, "default_vertex_attributes": {"x": 0.0, "y": 0.0, "z": 0.0}, "default_edge_attributes": {}, "default_face_attributes": {}, "vertex": {"0": {"x": 1801.059405019541, "y": -3000.0, "z": 376.06890166765487}, "1": {"x": 1859.7258351504702, "y": -3000.0, "z": 619.0879337941382}, "2": {"x": 605.3748859402758, "y": -3000.0, "z": 566.4725280590476}, "3": {"x": 625.0939375995681, "y": -3000.0, "z": 815.6936327064232}, "4": {"x": 1801.059405019541, "y": -2400.0, "z": 376.06890166765487}, "5": {"x": 1859.7258351504702, "y": -2400.0, "z": 619.0879337941382}, "6": {"x": 605.3748859402758, "y": -2400.0, "z": 566.4725280590476}, "7": {"x": 625.0939375995681, "y": -2400.0, "z": 815.6936327064232}}, "face": {"0": [0, 1, 3, 2], "1": [0, 4, 5, 1], "2": [4, 6, 7, 5], "3": [6, 2, 3, 7], "4": [1, 5, 7, 3], "5": [2, 6, 4, 0]}, "facedata": {"0": {}, "1": {}, "2": {}, "3": {}, "4": {}, "5": {}}, "edgedata": {}, "max_vertex": 7, "max_face": 5}, "guid": "489dac81-3b7e-4e3f-b33d-4cad18f5c6c4"}, {"dtype": "compas.datastructures/Mesh", "data": {"attributes": {"is_support": false}, "default_vertex_attributes": {"x": 0.0, "y": 0.0, "z": 0.0}, "default_edge_attributes": {}, "default_face_attributes": {}, "vertex": {"0": {"x": 1801.059405019541, "y": 2400.0, "z": 376.06890166765487}, "1": {"x": 1859.7258351504702, "y": 2400.0, "z": 619.0879337941382}, "2": {"x": 605.3748859402758, "y": 2400.0, "z": 566.4725280590476}, "3": {"x": 625.0939375995681, "y": 2400.0, "z": 815.6936327064232}, "4": {"x": 1801.059405019541, "y": 3000.0, "z": 376.06890166765487}, "5": {"x": 1859.7258351504702, "y": 3000.0, "z": 619.0879337941382}, "6": {"x": 605.3748859402758, "y": 3000.0, "z": 566.4725280590476}, "7": {"x": 625.0939375995681, "y": 3000.0, "z": 815.6936327064232}}, "face": {"0": [0, 1, 3, 2], "1": [0, 4, 5, 1], "2": [4, 6, 7, 5], "3": [6, 2, 3, 7], "4": [1, 5, 7, 3], "5": [2, 6, 4, 0]}, "facedata": {"0": {}, "1": {}, "2": {}, "3": {}, "4": {}, "5": {}}, "edgedata": {}, "max_vertex": 7, "max_face": 5}, "guid": "ca8cd869-66b7-4eb0-b38c-9a4399fe58b2"}, {"dtype": "compas.datastructures/Mesh", "data": {"attributes": {"is_support": false}, "default_vertex_attributes": {"x": 0.0, "y": 0.0, "z": 0.0}, "default_edge_attributes": {}, "default_face_attributes": {}, "vertex": {"0": {"x": -605.3748859402749, "y": -3000.0, "z": 566.4725280590478}, "1": {"x": -625.0939375995672, "y": -3000.0, "z": 815.6936327064236}, "2": {"x": -1801.05940501954, "y": -3000.0, "z": 376.0689016676545}, "3": {"x": -1859.7258351504697, "y": -3000.0, "z": 619.0879337941378}, "4": {"x": -605.3748859402749, "y": -2400.0, "z": 566.4725280590478}, "5": {"x": -625.0939375995672, "y": -2400.0, "z": 815.6936327064236}, "6": {"x": -1801.05940501954, "y": -2400.0, "z": 376.0689016676545}, "7": {"x": -1859.7258351504697, "y": -2400.0, "z": 619.0879337941378}}, "face": {"0": [0, 1, 3, 2], "1": [0, 4, 5, 1], "2": [4, 6, 7, 5], "3": [6, 2, 3, 7], "4": [1, 5, 7, 3], "5": [2, 6, 4, 0]}, "facedata": {"0": {}, "1": {}, "2": {}, "3": {}, "4": {}, "5": {}}, "edgedata": {}, "max_vertex": 7, "max_face": 5}, "guid": "b2b165ce-6171-4d7d-aad9-953a26ee8b0d"}, {"dtype": "compas.datastructures/Mesh", "data": {"attributes": {"is_support": false}, "default_vertex_attributes": {"x": 0.0, "y": 0.0, "z": 0.0}, "default_edge_attributes": {}, "default_face_attributes": {}, "vertex": {"0": {"x": -605.3748859402749, "y": 2400.0, "z": 566.4725280590478}, "1": {"x": -625.0939375995672, "y": 2400.0, "z": 815.6936327064236}, "2": {"x": -1801.05940501954, "y": 2400.0, "z": 376.0689016676545}, "3": {"x": -1859.7258351504697, "y": 2400.0, "z": 619.0879337941378}, "4": {"x": -605.3748859402749, "y": 3000.0, "z": 566.4725280590478}, "5": {"x": -625.0939375995672, "y": 3000.0, "z": 815.6936327064236}, "6": {"x": -1801.05940501954, "y": 3000.0, "z": 376.0689016676545}, "7": {"x": -1859.7258351504697, "y": 3000.0, "z": 619.0879337941378}}, "face": {"0": [0, 1, 3, 2], "1": [0, 4, 5, 1], "2": [4, 6, 7, 5], "3": [6, 2, 3, 7], "4": [1, 5, 7, 3], "5": [2, 6, 4, 0]}, "facedata": {"0": {}, "1": {}, "2": {}, "3": {}, "4": {}, "5": {}}, "edgedata": {}, "max_vertex": 7, "max_face": 5}, "guid": "aff35c63-edd0-402d-83c7-eee33f92e2b5"}], "Model::Frame::Frame": [{"dtype": "compas.geometry/Frame", "data": {"point": [2376.491240971309, -2400.0, 188.0344508338276], "xaxis": [0.9505380043276829, 0.0, -0.31060827794626783], "yaxis": [1.2246823880766735e-17, 0.9999999999999999, 3.747830420987818e-17]}, "guid": "48c6ecab-6c86-4520-ac5b-5fc091ee0c26"}, {"dtype": "compas.geometry/Frame", "data": {"point": [1203.2171454799084, -1800.0, 471.27071486335126], "xaxis": [0.9875570880530613, 0.0, -0.15726092278807993], "yaxis": [-3.1002825125054145e-18, 1.0000000000000002, -1.9468955897693276e-17]}, "guid": "ca80dc35-94a8-4969-9821-622ab1cbb0bb"}, {"dtype": "compas.geometry/Frame", "data": {"point": [4.547473508864641e-13, -2400.0, 566.4725280590477], "xaxis": [1.0, 0.0, -1.8779576153879642e-16], "yaxis": [-0.0, 1.0, 0.0]}, "guid": "513c15c1-d003-4f40-9916-892ec4d0fa9d"}, {"dtype": "compas.geometry/Frame", "data": {"point": [-1203.2171454799075, -1800.0, 471.27071486335115], "xaxis": [0.9875570880530611, 0.0, 0.15726092278808043], "yaxis": [3.100282512505425e-18, 1.0, -1.9468955897693276e-17]}, "guid": "b3fa834e-b3a5-467f-9773-8bb62294bd15"}, {"dtype": "compas.geometry/Frame", "data": {"point": [-2376.491240971309, -2400.0, 188.03445083382724], "xaxis": [0.950538004327683, 0.0, 0.31060827794626744], "yaxis": [1.2246823880766726e-17, 1.0, -3.7478304209878203e-17]}, "guid": "acfc18cf-2140-4057-a8ff-ba8453d970f7"}, {"dtype": "compas.geometry/Frame", "data": {"point": [2376.491240971309, -1200.0, 188.0344508338276], "xaxis": [0.9505380043276829, 0.0, -0.31060827794626783], "yaxis": [1.2246823880766735e-17, 0.9999999999999999, 3.747830420987818e-17]}, "guid": "e1547f8e-9723-4e00-b4dc-32d97ccd7f85"}, {"dtype": "compas.geometry/Frame", "data": {"point": [1203.2171454799084, -600.0, 471.27071486335126], "xaxis": [0.9875570880530613, 0.0, -0.15726092278807993], "yaxis": [-3.1002825125054145e-18, 1.0000000000000002, -1.9468955897693276e-17]}, "guid": "0ba37ff5-5447-4c66-8cf1-fa376f2bebd9"}, {"dtype": "compas.geometry/Frame", "data": {"point": [4.547473508864641e-13, -1200.0, 566.4725280590477], "xaxis": [1.0, 0.0, -1.8779576153879642e-16], "yaxis": [-0.0, 1.0, 0.0]}, "guid": "40147d7a-ced1-48e5-bebe-f775509568cf"}, {"dtype": "compas.geometry/Frame", "data": {"point": [-1203.2171454799075, -600.0, 471.27071486335115], "xaxis": [0.9875570880530611, 0.0, 0.15726092278808043], "yaxis": [3.100282512505425e-18, 1.0, -1.9468955897693276e-17]}, "guid": "6bd15abb-1106-49eb-84db-3f7177139065"}, {"dtype": "compas.geometry/Frame", "data": {"point": [-2376.491240971309, -1200.0, 188.03445083382724], "xaxis": [0.950538004327683, 0.0, 0.31060827794626744], "yaxis": [1.2246823880766726e-17, 1.0, -3.7478304209878203e-17]}, "guid": "afc57226-1123-47bf-a3db-8fe782405c1d"}, {"dtype": "compas.geometry/Frame", "data": {"point": [2376.491240971309, 0.0, 188.0344508338276], "xaxis": [0.9505380043276829, 0.0, -0.31060827794626783], "yaxis": [1.2246823880766735e-17, 0.9999999999999999, 3.747830420987818e-17]}, "guid": "8d856c62-5a58-495d-91cc-70a9717f3bf0"}, {"dtype": "compas.geometry/Frame", "data": {"point": [1203.2171454799084, 600.0, 471.27071486335126], "xaxis": [0.9875570880530613, 0.0, -0.15726092278807993], "yaxis": [-3.1002825125054145e-18, 1.0000000000000002, -1.9468955897693276e-17]}, "guid": "d98a2e0a-96de-4775-a51b-a4aa1501a639"}, {"dtype": "compas.geometry/Frame", "data": {"point": [4.547473508864641e-13, 0.0, 566.4725280590477], "xaxis": [1.0, 0.0, -1.8779576153879642e-16], "yaxis": [-0.0, 1.0, 0.0]}, "guid": "0192974d-4522-4dc5-85d0-cc0ef05d8104"}, {"dtype": "compas.geometry/Frame", "data": {"point": [-1203.2171454799075, 600.0, 471.27071486335115], "xaxis": [0.9875570880530611, 0.0, 0.15726092278808043], "yaxis": [3.100282512505425e-18, 1.0, -1.9468955897693276e-17]}, "guid": "0a30f8fa-0c19-4b08-8838-e45b624ad933"}, {"dtype": "compas.geometry/Frame", "data": {"point": [-2376.491240971309, 0.0, 188.03445083382724], "xaxis": [0.950538004327683, 0.0, 0.31060827794626744], "yaxis": [1.2246823880766726e-17, 1.0, -3.7478304209878203e-17]}, "guid": "1b79187a-13d3-44b9-98c3-93cc2aea0d43"}, {"dtype": "compas.geometry/Frame", "data": {"point": [2376.491240971309, 1200.0, 188.0344508338276], "xaxis": [0.9505380043276829, 0.0, -0.31060827794626783], "yaxis": [1.2246823880766735e-17, 0.9999999999999999, 3.747830420987818e-17]}, "guid": "b179046d-e2e7-4b7d-88bb-d43b620ae6d0"}, {"dtype": "compas.geometry/Frame", "data": {"point": [1203.2171454799084, 1800.0, 471.27071486335126], "xaxis": [0.9875570880530613, 0.0, -0.15726092278807993], "yaxis": [-3.1002825125054145e-18, 1.0000000000000002, -1.9468955897693276e-17]}, "guid": "527e1d1c-3449-4ca3-a224-7b5fef497f7e"}, {"dtype": "compas.geometry/Frame", "data": {"point": [4.547473508864641e-13, 1200.0, 566.4725280590477], "xaxis": [1.0, 0.0, -1.8779576153879642e-16], "yaxis": [-0.0, 1.0, 0.0]}, "guid": "0f742cb1-590a-4c45-acba-ee3f05d2bf92"}, {"dtype": "compas.geometry/Frame", "data": {"point": [-1203.2171454799075, 1800.0, 471.27071486335115], "xaxis": [0.9875570880530611, 0.0, 0.15726092278808043], "yaxis": [3.100282512505425e-18, 1.0, -1.9468955897693276e-17]}, "guid": "3f3772e4-d4eb-494b-9ceb-cd7438a57ab6"}, {"dtype": "compas.geometry/Frame", "data": {"point": [-2376.491240971309, 1200.0, 188.03445083382724], "xaxis": [0.950538004327683, 0.0, 0.31060827794626744], "yaxis": [1.2246823880766726e-17, 1.0, -3.7478304209878203e-17]}, "guid": "3afac1e5-5ede-4b8c-9887-eb06e601ce69"}, {"dtype": "compas.geometry/Frame", "data": {"point": [2376.491240971309, 2400.0, 188.0344508338276], "xaxis": [0.9505380043276829, 0.0, -0.31060827794626783], "yaxis": [1.2246823880766735e-17, 0.9999999999999999, 3.747830420987818e-17]}, "guid": "219fbf7c-a738-411a-9416-a2eaa7f092c5"}, {"dtype": "compas.geometry/Frame", "data": {"point": [4.547473508864641e-13, 2400.0, 566.4725280590477], "xaxis": [1.0, 0.0, -1.8779576153879642e-16], "yaxis": [-0.0, 1.0, 0.0]}, "guid": "ea78fc3f-b28e-4149-9414-c08bf4ddc161"}, {"dtype": "compas.geometry/Frame", "data": {"point": [-2376.491240971309, 2400.0, 188.03445083382724], "xaxis": [0.950538004327683, 0.0, 0.31060827794626744], "yaxis": [1.2246823880766726e-17, 1.0, -3.7478304209878203e-17]}, "guid": "b6a31a59-9ec4-41ed-9c40-4020a2e26086"}, {"dtype": "compas.geometry/Frame", "data": {"point": [1203.2171454799084, -2700.0, 471.27071486335126], "xaxis": [0.9875570880530613, 0.0, -0.15726092278807993], "yaxis": [-0.0, 1.0000000000000002, 0.0]}, "guid": "35a5484b-4aeb-4538-865a-2c04bfe97d53"}, {"dtype": "compas.geometry/Frame", "data": {"point": [1203.2171454799084, 2700.0, 471.27071486335126], "xaxis": [0.9875570880530613, 0.0, -0.15726092278807993], "yaxis": [-0.0, 1.0000000000000002, 0.0]}, "guid": "4903dc33-9fd2-456b-a211-00c9e86cdcc9"}, {"dtype": "compas.geometry/Frame", "data": {"point": [-1203.2171454799075, -2700.0, 471.27071486335115], "xaxis": [0.9875570880530611, 0.0, 0.15726092278808043], "yaxis": [0.0, 1.0, -0.0]}, "guid": "91cb5ece-e928-4f53-a91f-4caf92293b98"}, {"dtype": "compas.geometry/Frame", "data": {"point": [-1203.2171454799075, 2700.0, 471.27071486335115], "xaxis": [0.9875570880530611, 0.0, 0.15726092278808043], "yaxis": [0.0, 1.0, -0.0]}, "guid": "6b38ddb8-6b3a-4117-9226-6de86ed6f116"}]}